leak/__init__.py
leak/cli.py
leak/main.py
leak/parser.py
leak/settings.py
leak/ui.py
leak/utils.py
leak-2.2.2.dist-info/LICENSE
leak-2.2.2.dist-info/METADATA
leak-2.2.2.dist-info/WHEEL
leak-2.2.2.dist-info/entry_points.txt
leak-2.2.2.dist-info/RECORD
