Metadata-Version: 2.3
Name: leak
Version: 2.2.2
Summary: Show release information about packages on PyPI
License: MIT
Keywords: pypi,package,info,cli,utility
Author: Misha Behersky
Author-email: bmwant@gmail.com
Requires-Python: >=3.9
Classifier: Development Status :: 5 - Production/Stable
Classifier: Environment :: Console
Classifier: Intended Audience :: Developers
Classifier: Intended Audience :: System Administrators
Classifier: License :: OSI Approved :: MIT License
Classifier: Operating System :: OS Independent
Classifier: Topic :: Utilities
Classifier: Topic :: Software Development :: Build Tools
Classifier: Topic :: Internet :: WWW/HTTP :: Indexing/Search
Classifier: Topic :: Software Development :: Libraries
Classifier: Topic :: Software Development :: Libraries :: Python Modules
Classifier: Topic :: System :: Archiving :: Packaging
Classifier: Programming Language :: Python :: 3
Classifier: Programming Language :: Python :: 3 :: Only
Classifier: Programming Language :: Python :: 3.9
Classifier: Programming Language :: Python :: 3.10
Classifier: Programming Language :: Python :: 3.11
Classifier: Programming Language :: Python :: 3.12
Classifier: Programming Language :: Python :: 3.13
Classifier: Programming Language :: Unix Shell
Requires-Dist: click (>=8.1.8,<8.2) ; python_version < "3.10"
Requires-Dist: click (>=8.2.1,<9.0.0) ; python_version >= "3.10"
Requires-Dist: packaging (>=25.0,<26.0)
Requires-Dist: pydantic (>=2.11.5,<3.0.0)
Requires-Dist: pydantic-settings (>=2.9.1,<3.0.0)
Requires-Dist: requests (>=2.32.3,<3.0.0)
Requires-Dist: rich (>=14.0.0,<15.0.0)
Project-URL: Homepage, https://bmwant.link/leak-package/
Project-URL: Repository, https://github.com/bmwant/leak
